gender-classifier-cnn/__init__.py
gender-classifier-cnn/pipeline.py
gender_classifier_cnn/__init__.py
gender_classifier_cnn/pipeline.py
model/__init__.py
model/cnn.py
model/my_model.py
preprocessing/__init__.py
preprocessing/my_dataloader.py
preprocessing/task_dataset.py
gender_classifier_cnn_usoltsev37-0.0.2.dist-info/LICENSE
gender_classifier_cnn_usoltsev37-0.0.2.dist-info/METADATA
gender_classifier_cnn_usoltsev37-0.0.2.dist-info/WHEEL
gender_classifier_cnn_usoltsev37-0.0.2.dist-info/top_level.txt
gender_classifier_cnn_usoltsev37-0.0.2.dist-info/RECORD
