Metadata-Version: 2.1
Name: gender-classifier-cnn-usoltsev37
Version: 0.0.2
Summary: hse-engineering-practices-gender-classifier-cnn
Home-page: https://github.com/usoltsev37/hse-engineering-practices-ml/tree/main/gender-classifier-cnn
Author: Nikita Usoltsev
Author-email: nikitav030301@gmail.com
License: UNKNOWN
Platform: UNKNOWN
Classifier: Programming Language :: Python :: 3.9
Classifier: License :: OSI Approved :: MIT License
Classifier: Operating System :: OS Independent
Requires-Python: ==3.9.12
License-File: LICENSE
Requires-Dist: contourpy (==1.0.6)
Requires-Dist: cycler (==0.11.0)
Requires-Dist: fonttools (==4.38.0)
Requires-Dist: kiwisolver (==1.4.4)
Requires-Dist: matplotlib (==3.6.2)
Requires-Dist: numpy (==1.23.5)
Requires-Dist: packaging (==21.3)
Requires-Dist: pandas (==1.5.1)
Requires-Dist: Pillow (==9.3.0)
Requires-Dist: pyparsing (==3.0.9)
Requires-Dist: python-dateutil (==2.8.2)
Requires-Dist: pytz (==2022.6)
Requires-Dist: six (==1.16.0)
Requires-Dist: torch (==1.13.0)
Requires-Dist: torchaudio (==0.13.0)
Requires-Dist: tqdm (==4.64.1)
Requires-Dist: typing-extensions (==4.4.0)
